little_server/__init__.py
little_server/server.py
little_server/utils/__init__.py
little_server/utils/utils.py
little_server-5.0.1.dist-info/LICENSE.txt
little_server-5.0.1.dist-info/WHEEL
little_server-5.0.1.dist-info/METADATA
little_server-5.0.1.dist-info/RECORD
