Metadata-Version: 2.1
Name: little-server
Version: 5.0.1
Summary: A dead simple server for personal websites
License: MIT
Author: megahomyak
Author-email: g.megahomyak@gmail.com
Requires-Python: >=3.7
Classifier: License :: OSI Approved :: MIT License
Classifier: Programming Language :: Python :: 3
Classifier: Programming Language :: Python :: 3.7
Classifier: Programming Language :: Python :: 3.8
Classifier: Programming Language :: Python :: 3.9
Classifier: Programming Language :: Python :: 3.10
Classifier: Programming Language :: Python :: 3.11
Requires-Dist: Markdown (>=3.4.1,<4.0.0)
Requires-Dist: docutils (>=0.19,<0.20)
Requires-Dist: fastapi (>=0.81.0,<0.82.0)
Requires-Dist: textile (>=4.0.2,<5.0.0)
